qrst/__init__.py
qrst/buff_mgr.py
qrst/perf_analyse.py
qrst/qr_code.py
qrst/qr_codec_util.py
qrst-0.1.0.dist-info/METADATA
qrst-0.1.0.dist-info/WHEEL
qrst-0.1.0.dist-info/top_level.txt
qrst-0.1.0.dist-info/RECORD
