Metadata-Version: 2.1
Name: qrst
Version: 0.1.0
Summary: QRST-AB or QRST is a  QR code-based secure transmission algorithm (QRST-AB) using Avro and Byte Pair Encoding (BPE)
Home-page: https://github.com/yourusername/qrst
Author: DrBreath
Author-email: cli@doclive.cn
Classifier: Programming Language :: Python :: 3
Classifier: License :: OSI Approved :: MIT License
Classifier: Operating System :: OS Independent
Requires-Python: >=3.8
Requires-Dist: numpy
Requires-Dist: sentencepiece
Requires-Dist: avro
